COPYING
MANIFEST.in
build.sh
get_package.sh
get_sources.sh
setup.py
versions.py
versions.sh
environment_modules.egg-info/PKG-INFO
environment_modules.egg-info/SOURCES.txt
environment_modules.egg-info/dependency_links.txt
environment_modules.egg-info/top_level.txt
vendor/environment-modules.tar.bz2