Metadata-Version: 2.1
Name: environment-modules
Version: 4.6.0.dev0
Summary: UNKNOWN
Home-page: UNKNOWN
License: UNKNOWN
Platform: linux
Classifier: License :: OSI Approved :: GNU General Public License v2 (GPLv2)
Classifier: Programming Language :: C
Classifier: Topic :: System
Classifier: Development Status :: 5 - Production/Stable
License-File: COPYING
